generator/__init__.py
generator/claim_data.py
generator/generator.py
generator/table_helpers.py
generator/structure/__init__.py
generator/structure/address.py
generator/structure/environment.py
generator/structure/vehicle.py
tests/__init__.py
tests/test_data.py
tests/test_table_helpers.py
ems_generator_pkg_MarkoDS-0.0.6.dist-info/LICENSE
ems_generator_pkg_MarkoDS-0.0.6.dist-info/METADATA
ems_generator_pkg_MarkoDS-0.0.6.dist-info/WHEEL
ems_generator_pkg_MarkoDS-0.0.6.dist-info/top_level.txt
ems_generator_pkg_MarkoDS-0.0.6.dist-info/RECORD
