Metadata-Version: 2.1
Name: ems-generator-pkg-MarkoDS
Version: 0.0.6
Summary: Library to generate .ad1, .ad2, .veh, .env by CIECA         estimate management standard
Home-page: https://github.com/acdcorp/autolink_ems_generator
Author: Marko Kauzlarić
Author-email: marko@discoveryspecialists.com
License: UNKNOWN
Platform: UNKNOWN
Classifier: Programming Language :: Python :: 3
Classifier: License :: OSI Approved :: MIT License
Classifier: Operating System :: OS Independent
Requires-Python: >=3.7
Requires-Dist: dbf
